makecents_exceptions/___init__.py
makecents_exceptions/exceptions.py
makecents_exceptions-0.0.4.dist-info/LICENSE
makecents_exceptions-0.0.4.dist-info/METADATA
makecents_exceptions-0.0.4.dist-info/WHEEL
makecents_exceptions-0.0.4.dist-info/top_level.txt
makecents_exceptions-0.0.4.dist-info/RECORD
