Metadata-Version: 2.1
Name: makecents-exceptions
Version: 0.0.4
Summary: exceptions package
Home-page: https://github.com/MakeCents-NYC/makecents-exceptionst
Author: MakeCents
Author-email: yma@mymakecents.com
License: UNKNOWN
Platform: UNKNOWN
Classifier: Programming Language :: Python :: 3
Classifier: License :: OSI Approved :: GNU General Public License v3 (GPLv3)
Classifier: Operating System :: OS Independent
